stamdata3/Employment.py
stamdata3/Organisation.py
stamdata3/Relation.py
stamdata3/Resource.py
stamdata3/StamdataExceptions.py
stamdata3/XMLDataHelper.py
stamdata3/__init__.py
stamdata3/stamdata3.py
stamdata3/tests/__init__.py
stamdata3/tests/test_employment.py
stamdata3/tests/test_resource.py
stamdata3/tests/test_stamdata.py
stamdata3-1.0.2.dist-info/LICENSE
stamdata3-1.0.2.dist-info/METADATA
stamdata3-1.0.2.dist-info/WHEEL
stamdata3-1.0.2.dist-info/top_level.txt
stamdata3-1.0.2.dist-info/RECORD
